core_engine/__init__.py
core_engine/connection.py
core_engine/constants.py
core_engine/auth/__init__.py
core_engine/auth/services.py
core_engine/bridges/__init__.py
core_engine/bridges/access.py
core_engine/bridges/integration.py
core_engine/caches/__init__.py
core_engine/caches/services.py
core_engine/connectivity/__init__.py
core_engine/connectivity/query_builder.py
core_engine/connectivity/services.py
core_engine/custom_query/__init__.py
core_engine/external_integration/__init__.py
core_engine/external_integration/services.py
core_engine/queueing/__init__.py
core_engine/queueing/queue.py
core_engine/utilities/__init__.py
core_engine/utilities/paginations.py
core_engine/utilities/utils.py
core_engine/utilities/validator.py
ebesha_core_engine-0.1.4.dist-info/METADATA
ebesha_core_engine-0.1.4.dist-info/WHEEL
ebesha_core_engine-0.1.4.dist-info/top_level.txt
ebesha_core_engine-0.1.4.dist-info/RECORD
